simpledht/__init__.py
simpledht/cli.py
simpledht/dht_node.py
simpledht/test_dht.py
simpledht-0.1.4.dist-info/licenses/LICENSE
simpledht-0.1.4.dist-info/METADATA
simpledht-0.1.4.dist-info/WHEEL
simpledht-0.1.4.dist-info/entry_points.txt
simpledht-0.1.4.dist-info/top_level.txt
simpledht-0.1.4.dist-info/RECORD
