Metadata-Version: 2.4
Name: simpledht
Version: 0.1.4
Summary: A simple distributed hash table implementation
Home-page: https://github.com/dhruvldrp9/simpledht
Author: Dhruvkumar Patel
Author-email: dhruv.ldrp9@gmail.com
Classifier: Programming Language :: Python :: 3
Classifier: License :: OSI Approved :: MIT License
Classifier: Operating System :: OS Independent
Requires-Python: >=3.6
License-File: LICENSE
Requires-Dist: requests>=2.25.1
Requires-Dist: click>=8.0.1
Dynamic: author
Dynamic: author-email
Dynamic: classifier
Dynamic: description
Dynamic: description-content-type
Dynamic: home-page
Dynamic: license-file
Dynamic: requires-dist
Dynamic: requires-python
Dynamic: summary
